Metadata-Version: 1.0
Name: packagemaketest
Version: 0.5
Summary: The funniest joke in Japan
Home-page: http://github.com/xinkent/packagemaketest.git
Author: K Xin
Author-email: xinkent1994@gmail.com
License: MIT
Platform: UNKNOWN
